[
  {
    "video_id": "Hnvs0lwKngY",
    "url": "https://www.youtube.com/watch?v=Hnvs0lwKngY",
    "title": "Ravi Gupta Roasts Non-Stop! 🤣 10 Mins of Madness | PGX #88 @raviguptacomedy​",
    "views": 281597,
    "channel_name": "PGX Clips",
    "thumbnail_path": "thumbnails/videos/Hnvs0lwKngY.jpg",
    "channel_logo_path": "thumbnails/channels/PGX_Clips_UCf6OuKUosovwkfr44t6qO9Q.jpg",
    "is_short": false
  },
  {
    "video_id": "voN-LFwJtPc",
    "url": "https://www.youtube.com/watch?v=voN-LFwJtPc&list=RDvoN-LFwJtPc&start_radio=1&pp=oAcB",
    "title": "30 Minutes of Peace Vol.3 - Best of Bollywood Lofi Mixtape to relax/chill/study/drive",
    "views": 5450093,
    "channel_name": "Lo-fi 2307",
    "thumbnail_path": "thumbnails/videos/voN-LFwJtPc.jpg",
    "channel_logo_path": "thumbnails/channels/Lo-fi_2307_UCh7aocZezr9gnY0uh0uONVA.jpg",
    "is_short": false
  },
  {
    "video_id": "jrtGS5MscqA",
    "url": "https://www.youtube.com/watch?v=jrtGS5MscqA",
    "title": "Ben 10’s FIRST TIME With the OMNITRIX 👽 | Hindi Clip | Netflix India",
    "views": 89392,
    "channel_name": "Netflix India",
    "thumbnail_path": "thumbnails/videos/jrtGS5MscqA.jpg",
    "channel_logo_path": "thumbnails/channels/Netflix_India_UCZSNzBgFub_WWil6TOTYwAg.jpg",
    "is_short": false
  },
  {
    "video_id": "DNDY75s8hus",
    "url": "https://www.youtube.com/watch?v=DNDY75s8hus",
    "title": "Munawar Faruqui Got Roasted | Playground Season 4 | Elvish Yadav, Mythpat, Mortal | Amazon MX Player",
    "views": 6702351,
    "channel_name": "Amazon MX Player",
    "thumbnail_path": "thumbnails/videos/DNDY75s8hus.jpg",
    "channel_logo_path": "thumbnails/channels/Amazon_MX_Player_UC1NtcHxG3wiyhtbbPmIaMnA.jpg",
    "is_short": false
  },
  {
    "video_id": "XLYAz6yuJOk",
    "url": "https://www.youtube.com/watch?v=XLYAz6yuJOk",
    "title": "Transformers' Most Exciting Scenes",
    "views": 20240202,
    "channel_name": "Movieclips",
    "thumbnail_path": "thumbnails/videos/XLYAz6yuJOk.jpg",
    "channel_logo_path": "thumbnails/channels/Movieclips_UC3gNmTGu-TTbFPpfSs5kNkg.jpg",
    "is_short": false
  },
  {
    "video_id": "SSjhVR6yw3M",
    "url": "https://www.youtube.com/watch?v=SSjhVR6yw3M&pp=0gcJCccJAYcqIYzv",
    "title": "Bhide kaha Nikla Nimbu Ka ठेला लेके?! | FULL MOVIE | Taarak Mehta Ka Ooltah Chashmah",
    "views": 1142880,
    "channel_name": "Taarak Mehta Ka Ooltah Chashmah",
    "thumbnail_path": "thumbnails/videos/SSjhVR6yw3M.jpg",
    "channel_logo_path": "thumbnails/channels/Taarak_Mehta_Ka_Ooltah_Chashmah_UCnSFZ-olBoLGLRUS_3RI2Aw.jpg",
    "is_short": false
  },
  {
    "video_id": "miZ0vI1lSZw",
    "url": "https://www.youtube.com/watch?v=miZ0vI1lSZw",
    "title": "@FlyingBeast320 brings Beast Life to Shark Tank India | Beast Vs Sharks | Full Pitch",
    "views": 7658811,
    "channel_name": "SET India",
    "thumbnail_path": "thumbnails/videos/miZ0vI1lSZw.jpg",
    "channel_logo_path": "thumbnails/channels/SET_India_UCpEhnqL0y41EpW2TvWAHD7Q.jpg",
    "is_short": false
  },
  {
    "video_id": "8qcQX3BJPdE",
    "url": "https://www.youtube.com/watch?v=8qcQX3BJPdE",
    "title": "Kullu ने Kusha Kapila के Ashish Solanki और Samay Raina वाले roast के पीछे की सच्चाई बताई",
    "views": 811620,
    "channel_name": "Lallantop Cinema",
    "thumbnail_path": "thumbnails/videos/8qcQX3BJPdE.jpg",
    "channel_logo_path": "thumbnails/channels/Lallantop_Cinema_UCXmUVmeWmuAU6kUqvczMvrg.jpg",
    "is_short": false
  },
  {
    "video_id": "f37Y6BE3D-c",
    "url": "https://www.youtube.com/watch?v=f37Y6BE3D-c",
    "title": "Har Boys Hostel Ki Problem😬 | Campus Diaries | Harsh Beniwal, Ritvik Sahore | Amazon MX Player",
    "views": 211608,
    "channel_name": "MX Player",
    "thumbnail_path": "thumbnails/videos/f37Y6BE3D-c.jpg",
    "channel_logo_path": "thumbnails/channels/MX_Player_UC6q2O2pOJ-LiFKm4w2EW73w.jpg",
    "is_short": false
  },
  {
    "video_id": "xfoq_aZD62w",
    "url": "https://www.youtube.com/watch?v=xfoq_aZD62w",
    "title": "Entire Story of BEN 10 in 34 Minutes HINDI*| Ben 10 Classic Explained |",
    "views": 478457,
    "channel_name": "ToonZila",
    "thumbnail_path": "thumbnails/videos/xfoq_aZD62w.jpg",
    "channel_logo_path": "thumbnails/channels/ToonZila_UCMgyZ4cAJYUPRmGAkoqPpGA.jpg",
    "is_short": false
  },
  {
    "video_id": "EmsRACUM4V4",
    "url": "https://www.youtube.com/watch?v=EmsRACUM4V4&list=RDEmsRACUM4V4&start_radio=1&pp=oAcB",
    "title": "Download unavailable",
    "views": 354126,
    "channel_name": "Divya Healing",
    "thumbnail_path": "thumbnails/videos/EmsRACUM4V4.jpg",
    "channel_logo_path": "thumbnails/channels/Divya_Healing_UCo96LUp3_IrAzMFpdyiavVg.jpg",
    "is_short": false
  },
  {
    "video_id": "PJ3ZQk_lr9E",
    "url": "https://www.youtube.com/watch?v=PJ3ZQk_lr9E",
    "title": "BB Ki Vines- | Ghar Kalesh |",
    "views": 26469450,
    "channel_name": "BB Ki Vines",
    "thumbnail_path": "thumbnails/videos/PJ3ZQk_lr9E.jpg",
    "channel_logo_path": "thumbnails/channels/BB_Ki_Vines_UCqwUrj10mAEsqezcItqvwEw.jpg",
    "is_short": false
  },
  {
    "video_id": "GgIbbpL7yJ0",
    "url": "https://www.youtube.com/watch?v=GgIbbpL7yJ0",
    "title": "ये Car कोई केकड़ा है क्या ? Rajpal Yadav का हिट डायलॉग | Taarzan The Wonder Car",
    "views": 1941622,
    "channel_name": "Haste Raho Comedy",
    "thumbnail_path": "thumbnails/videos/GgIbbpL7yJ0.jpg",
    "channel_logo_path": "thumbnails/channels/Haste_Raho_Comedy_UCnfQqtKFxoxwAI3mpdVeW9w.jpg",
    "is_short": false
  },
  {
    "video_id": "G5FWyaoTIAA",
    "url": "https://www.youtube.com/shorts/G5FWyaoTIAA",
    "title": "Subscribe",
    "views": 753774,
    "channel_name": "Satya Shreshtha",
    "thumbnail_path": "thumbnails/shorts/G5FWyaoTIAA.jpg",
    "channel_logo_path": "thumbnails/channels/Satya_Shreshtha_UCQiE8llNiuEDpaQuyXwBzeg.jpg",
    "is_short": true
  },
  {
    "video_id": "ggznQ4rP-I8",
    "url": "https://www.youtube.com/shorts/ggznQ4rP-I8",
    "title": "Subscribe",
    "views": 5376123,
    "channel_name": "Harsh Gujral Shorts",
    "thumbnail_path": "thumbnails/shorts/ggznQ4rP-I8.jpg",
    "channel_logo_path": "thumbnails/channels/Harsh_Gujral_Shorts_UCy23OPimCtLl2ZkumnTFo_A.jpg",
    "is_short": true
  },
  {
    "video_id": "186baYQq5-c",
    "url": "https://www.youtube.com/shorts/186baYQq5-c",
    "title": "Subscribe",
    "views": 2558052,
    "channel_name": "Hari Darshan Scope",
    "thumbnail_path": "thumbnails/shorts/186baYQq5-c.jpg",
    "channel_logo_path": "thumbnails/channels/Hari_Darshan_Scope_UCRw-HnQ7O2DkudcYFO9FQtw.jpg",
    "is_short": true
  },
  {
    "video_id": "lTevIDVBJR8",
    "url": "https://www.youtube.com/shorts/lTevIDVBJR8",
    "title": "Subscribe",
    "views": 6436864,
    "channel_name": "ADMD Comedy Dhamaka",
    "thumbnail_path": "thumbnails/shorts/lTevIDVBJR8.jpg",
    "channel_logo_path": "thumbnails/channels/ADMD_Comedy_Dhamaka_UCeLP0EN7XxLnhJ4HB3mtVcg.jpg",
    "is_short": true
  }
]